Metadata-Version: 2.1
Name: ZaidPy
Version: 0.1
Summary: Zaid program
Home-page: UNKNOWN
Author: Zaid
Author-email: fhdhasd39@gmail.com
License: UNKNOWN
Platform: UNKNOWN
Classifier: Programming Language :: Python :: 3
Classifier: Operating System :: OS Independent
Classifier: License :: OSI Approved :: MIT License
